skale/__init__.py
skale/config.py
skale/skale_allocator.py
skale/skale_base.py
skale/skale_ima.py
skale/skale_manager.py
skale/contracts/__init__.py
skale/contracts/base_contract.py
skale/contracts/contract_manager.py
skale/contracts/allocator/__init__.py
skale/contracts/allocator/allocator.py
skale/contracts/allocator/escrow.py
skale/contracts/ima/__init__.py
skale/contracts/ima/linker.py
skale/contracts/manager/__init__.py
skale/contracts/manager/bounty_v2.py
skale/contracts/manager/constants_holder.py
skale/contracts/manager/dkg.py
skale/contracts/manager/groups.py
skale/contracts/manager/key_storage.py
skale/contracts/manager/manager.py
skale/contracts/manager/node_rotation.py
skale/contracts/manager/nodes.py
skale/contracts/manager/punisher.py
skale/contracts/manager/schains.py
skale/contracts/manager/schains_internal.py
skale/contracts/manager/sync_manager.py
skale/contracts/manager/token.py
skale/contracts/manager/wallets.py
skale/contracts/manager/delegation/__init__.py
skale/contracts/manager/delegation/delegation_controller.py
skale/contracts/manager/delegation/delegation_period_manager.py
skale/contracts/manager/delegation/distributor.py
skale/contracts/manager/delegation/slashing_table.py
skale/contracts/manager/delegation/token_state.py
skale/contracts/manager/delegation/validator_service.py
skale/contracts/manager/test/__init__.py
skale/contracts/manager/test/time_helpers_with_debug.py
skale/dataclasses/__init__.py
skale/dataclasses/delegation_status.py
skale/dataclasses/node_info.py
skale/dataclasses/schain_options.py
skale/dataclasses/skaled_ports.py
skale/schain_config/__init__.py
skale/schain_config/generator.py
skale/schain_config/ports_allocation.py
skale/schain_config/rotation_history.py
skale/transactions/__init__.py
skale/transactions/exceptions.py
skale/transactions/result.py
skale/transactions/tools.py
skale/utils/__init__.py
skale/utils/abi_utils.py
skale/utils/account_tools.py
skale/utils/constants.py
skale/utils/contract_info.py
skale.py-6.4.dist-info/LICENSE
skale.py-6.4.dist-info/METADATA
skale.py-6.4.dist-info/WHEEL
skale.py-6.4.dist-info/top_level.txt
skale.py-6.4.dist-info/RECORD
